device_inductance/__init__.py
device_inductance/circuits.py
device_inductance/coils.py
device_inductance/contour.py
device_inductance/device.py
device_inductance/forces.py
device_inductance/grid.py
device_inductance/local.py
device_inductance/logging.py
device_inductance/mesh.py
device_inductance/model_reduction.py
device_inductance/mutuals.py
device_inductance/py.typed
device_inductance/sensors.py
device_inductance/tables.py
device_inductance/utils.py
device_inductance/structures/__init__.py
device_inductance/structures/filament.py
device_inductance/structures/heuristics.py
device_inductance/structures/input.py
device_inductance/structures/loop.py
device_inductance/structures/slicer.py
device_inductance-3.2.1.dist-info/METADATA
device_inductance-3.2.1.dist-info/WHEEL
device_inductance-3.2.1.dist-info/licenses/LICENSE-APACHE
device_inductance-3.2.1.dist-info/licenses/LICENSE-MIT
device_inductance-3.2.1.dist-info/RECORD
