Metadata-Version: 2.4
Name: device_inductance
Version: 3.2.1
Summary: Tokamak core inductance matrices and flux tables
Author-email: Commonwealth Fusion Systems <jlogan@cfs.energy>
License-Expression: MIT OR Apache-2.0
License-File: LICENSE-APACHE
License-File: LICENSE-MIT
Classifier: Development Status :: 5 - Production/Stable
Classifier: Intended Audience :: Science/Research
Classifier: Programming Language :: Python :: 3
Classifier: Programming Language :: Python :: 3 :: Only
Classifier: Programming Language :: Python :: 3.10
Classifier: Programming Language :: Python :: 3.11
Classifier: Programming Language :: Python :: 3.12
Classifier: Programming Language :: Python :: 3.13
Classifier: Topic :: Scientific/Engineering :: Physics
Requires-Python: <3.14,>=3.10
Requires-Dist: cfsem<4,>=3
Requires-Dist: gmsh<5,>=4.13.1
Requires-Dist: interpn[pydantic]<0.8,>=0.7
Requires-Dist: numpy<3,>=2
Requires-Dist: omas>=0.94.0
Requires-Dist: rich<15,>=14.0.0
Requires-Dist: scipy~=1.12
Requires-Dist: shapely<3,>=2.1.0
Provides-Extra: dev
Requires-Dist: coverage==7.10.2; extra == 'dev'
Requires-Dist: matplotlib<4,>=3.9.1; extra == 'dev'
Requires-Dist: mkdocs-material>=9.6.12; extra == 'dev'
Requires-Dist: mkdocs>=1.6.0; extra == 'dev'
Requires-Dist: mkdocstrings[python]>=0.29.1; extra == 'dev'
Requires-Dist: mktestdocs==0.2.4; extra == 'dev'
Requires-Dist: pyright==1.1.403; extra == 'dev'
Requires-Dist: pytest==8.4.1; extra == 'dev'
Requires-Dist: ruff==0.12.7; extra == 'dev'
